<?xml version="1.0" encoding="utf-8"?>
<xliff xmlns="urn:oasis:names:tc:xliff:document:1.2" xmlns:xsi="http://www.w3.org/2001/XMLSchema-instance" version="1.2" xsi:schemaLocation="urn:oasis:names:tc:xliff:document:1.2 xliff-core-1.2-transitional.xsd">
  <file datatype="xml" original="RoutingStrategy.xml" source-language="en-US" target-language="ja-JP">
    <header>
      <tool tool-id="mdxliff" tool-name="mdxliff" tool-version="1.0-15c36f0" tool-company="Microsoft" />
      <xliffext:skl_file_name xmlns:xliffext="urn:microsoft:content:schema:xliffextensions">02cd5861-7ce2-4a82-b358-31f8435a0ac58b1b08ce70f1c37f120f0b5d147eb9b760cc3997.skl</xliffext:skl_file_name>
      <xliffext:version xmlns:xliffext="urn:microsoft:content:schema:xliffextensions">1.2</xliffext:version>
      <xliffext:ms.openlocfilehash xmlns:xliffext="urn:microsoft:content:schema:xliffextensions">8b1b08ce70f1c37f120f0b5d147eb9b760cc3997</xliffext:ms.openlocfilehash>
      <xliffext:ms.sourcegitcommit xmlns:xliffext="urn:microsoft:content:schema:xliffextensions">d31dc2ede16f6f7bc64e90d9f897ff54c4e3869b</xliffext:ms.sourcegitcommit>
      <xliffext:ms.lasthandoff xmlns:xliffext="urn:microsoft:content:schema:xliffextensions">04/03/2018</xliffext:ms.lasthandoff>
      <xliffext:moniker_ids xmlns:xliffext="urn:microsoft:content:schema:xliffextensions">netframework-4.5.1,netframework-4.5.2,netframework-4.5,netframework-4.6.1,netframework-4.6.2,netframework-4.6,netframework-4.7.1,netframework-4.7</xliffext:moniker_ids>
    </header>
    <body>
      <group id="content" extype="content">
        <trans-unit id="101" translate="yes" xml:space="preserve" uid="T:System.Windows.RoutingStrategy">
          <source>Indicates the routing strategy of a routed event.</source>
          <target state="translated">ルーティング イベントのルーティング方法を示します。</target>       </trans-unit>
        <trans-unit id="102" translate="yes" xml:space="preserve" extradata="MT" uid="T:System.Windows.RoutingStrategy">
          <source>Routing strategy for each routed event must be only one of these values.</source>
          <target state="translated">各ルーティング イベントのルーティング方法は、これらの値の 1 つだけにする必要があります。</target>       </trans-unit>
        <trans-unit id="103" translate="yes" xml:space="preserve" extradata="MT" uid="T:System.Windows.RoutingStrategy">
          <source>However, input events often exist in pairs on base classes, where one event is the bubbling version and one event is the tunneling version.</source>
          <target state="translated">ただし、入力イベントは、基本クラスで、1 つのイベントがバブルのバージョンであり、1 つのイベントは、トンネルのバージョンのペアで多くの場合があります。</target>       </trans-unit>
        <trans-unit id="104" translate="yes" xml:space="preserve" extradata="MT" uid="T:System.Windows.RoutingStrategy">
          <source>For input events uniquely, the tunneling and bubbling versions have shared arguments and are raised in succession in response to the input device condition that raises the events.</source>
          <target state="translated">入力イベントの一意で、トンネリングとバブル バージョン引数を共有され、イベントを発生させる入力デバイスの状態への応答で連続して発生します。</target>       </trans-unit>
        <trans-unit id="105" translate="yes" xml:space="preserve" uid="F:System.Windows.RoutingStrategy.Bubble">
          <source>The routed event uses a bubbling strategy, where the event instance routes upwards through the tree, from event source to root.</source>
          <target state="translated">ルーティング イベントは、イベント インスタンスをルートからソース要素へとツリーを介して下方にルーティングするトンネル方法を使用します。</target>       </trans-unit>
        <trans-unit id="106" translate="yes" xml:space="preserve" uid="F:System.Windows.RoutingStrategy.Direct">
          <source>The routed event does not route through an element tree, but does support other routed event capabilities such as class handling, <ph id="ph1">&lt;see cref="T:System.Windows.EventTrigger" /&gt;</ph> or <ph id="ph2">&lt;see cref="T:System.Windows.EventSetter" /&gt;</ph>.</source>
          <target state="translated">ルーティング イベントは、要素ツリーを介してルーティングされません。ただし、クラス処理、<ph id="ph1">&lt;see cref="T:System.Windows.EventTrigger" /&gt;</ph>、または <ph id="ph2">&lt;see cref="T:System.Windows.EventSetter" /&gt;</ph> など、その他のルーティング イベント機能をサポートします。</target>       </trans-unit>
        <trans-unit id="107" translate="yes" xml:space="preserve" uid="F:System.Windows.RoutingStrategy.Tunnel">
          <source>The routed event uses a tunneling strategy, where the event instance routes downwards through the tree, from root to source element.</source>
          <target state="translated">ルーティング イベントは、イベント インスタンスをルートからソース要素へとツリーを介して下方にルーティングするトンネル方法を使用します。</target>       </trans-unit>
      </group>
    </body>
  </file>
</xliff>