<?xml version="1.0" encoding="utf-8"?>
<xliff xmlns="urn:oasis:names:tc:xliff:document:1.2" xmlns:xsi="http://www.w3.org/2001/XMLSchema-instance" version="1.2" xsi:schemaLocation="urn:oasis:names:tc:xliff:document:1.2 xliff-core-1.2-transitional.xsd">
  <file datatype="xml" original="WebGetAttribute.xml" source-language="en-US" target-language="ja-JP">
    <header>
      <tool tool-id="mdxliff" tool-name="mdxliff" tool-version="1.0-15c36f0" tool-company="Microsoft" />
      <xliffext:skl_file_name xmlns:xliffext="urn:microsoft:content:schema:xliffextensions">9575d09f-9d72-4690-889e-b83c405ca456a212c275aa9beebf9048f1bc98ddf5498c93b6d2.skl</xliffext:skl_file_name>
      <xliffext:version xmlns:xliffext="urn:microsoft:content:schema:xliffextensions">1.2</xliffext:version>
      <xliffext:ms.openlocfilehash xmlns:xliffext="urn:microsoft:content:schema:xliffextensions">a212c275aa9beebf9048f1bc98ddf5498c93b6d2</xliffext:ms.openlocfilehash>
      <xliffext:ms.sourcegitcommit xmlns:xliffext="urn:microsoft:content:schema:xliffextensions">254e16ae65e82f4aa59360cd8572b36b6b5b2f80</xliffext:ms.sourcegitcommit>
      <xliffext:ms.lasthandoff xmlns:xliffext="urn:microsoft:content:schema:xliffextensions">04/05/2018</xliffext:ms.lasthandoff>
      <xliffext:moniker_ids xmlns:xliffext="urn:microsoft:content:schema:xliffextensions">netframework-4.5.1,netframework-4.5.2,netframework-4.5,netframework-4.6.1,netframework-4.6.2,netframework-4.6,netframework-4.7.1,netframework-4.7.2,netframework-4.7,xamarinandroid-7.1,xamarinios-10.8,xamarinmac-3.0</xliffext:moniker_ids>
    </header>
    <body>
      <group id="content" extype="content">
        <trans-unit id="101" translate="yes" xml:space="preserve" uid="T:System.ServiceModel.Web.WebGetAttribute">
          <source>Represents an attribute indicating that a service operation is logically a retrieval operation and that it can be called by the WCF REST programming model.</source>
          <target state="translated">サービス操作が論理的には取得操作であり、WCF REST プログラミング モデルで呼び出すことができることを示す属性を表します。</target>       </trans-unit>
        <trans-unit id="102" translate="yes" xml:space="preserve" extradata="MT" uid="T:System.ServiceModel.Web.WebGetAttribute">
          <source>The <ph id="ph1">&lt;xref:System.ServiceModel.Web.WebGetAttribute&gt;</ph> attribute is applied to a service operation in addition to the <ph id="ph2">&lt;xref:System.ServiceModel.OperationContractAttribute&gt;</ph> and associates the operation with a <ph id="ph3">&lt;xref:System.UriTemplate&gt;</ph> as well as the HTTP protocol Get verb.</source>
          <target state="translated"><ph id="ph1">&lt;xref:System.ServiceModel.Web.WebGetAttribute&gt;</ph> 属性は、<ph id="ph2">&lt;xref:System.ServiceModel.OperationContractAttribute&gt;</ph> に加えてサービス操作に適用され、その操作を、HTTP プロトコルの Get 動詞と同様に <ph id="ph3">&lt;xref:System.UriTemplate&gt;</ph> と関連付けます。</target>       </trans-unit>
        <trans-unit id="103" translate="yes" xml:space="preserve" extradata="MT" uid="T:System.ServiceModel.Web.WebGetAttribute">
          <source>The association with HTTP Get verb means that the operation is used to retrieve information from the service.</source>
          <target state="translated">HTTP の Get 動詞と関連付けるということは、その操作がサービスから情報を取得するために使用されることを意味します。</target>       </trans-unit>
        <trans-unit id="104" translate="yes" xml:space="preserve" extradata="MT" uid="T:System.ServiceModel.Web.WebGetAttribute">
          <source>The <ph id="ph1">&lt;xref:System.ServiceModel.Web.WebGetAttribute&gt;</ph> attribute is a <bpt id="p1">*</bpt>passive<ept id="p1">*</ept> operation behavior (the <ph id="ph2">&lt;xref:System.ServiceModel.Description.IOperationBehavior&gt;</ph> methods do nothing) that adds metadata to the operation description.</source>
          <target state="translated"><ph id="ph1">&lt;xref:System.ServiceModel.Web.WebGetAttribute&gt;</ph>属性は、<bpt id="p1">*</bpt>パッシブ<ept id="p1">*</ept>操作の動作 (、<ph id="ph2">&lt;xref:System.ServiceModel.Description.IOperationBehavior&gt;</ph>メソッドは、何もしない) にメタデータ操作の説明を追加します。</target>       </trans-unit>
        <trans-unit id="105" translate="yes" xml:space="preserve" extradata="MT" uid="T:System.ServiceModel.Web.WebGetAttribute">
          <source>Applying the <ph id="ph1">&lt;xref:System.ServiceModel.Web.WebGetAttribute&gt;</ph> attribute to a service operation has no effect unless a behavior that is looking for this metadata in the operation description (such as <ph id="ph2">&lt;xref:System.ServiceModel.Description.WebHttpBehavior&gt;</ph>) is added to the service's behavior collection.</source>
          <target state="translated">このメタデータを操作の説明で検索する動作 (<ph id="ph1">&lt;xref:System.ServiceModel.Web.WebGetAttribute&gt;</ph> など) がサービスの動作コレクションに追加されていない場合は、<ph id="ph2">&lt;xref:System.ServiceModel.Description.WebHttpBehavior&gt;</ph> 属性をサービス操作に適用しても機能しません。</target>       </trans-unit>
        <trans-unit id="106" translate="yes" xml:space="preserve" extradata="MT" uid="T:System.ServiceModel.Web.WebGetAttribute">
          <source>Service operations with the <ph id="ph1">&lt;xref:System.ServiceModel.Web.WebGetAttribute&gt;</ph> attribute applied should be logical retrieval operations.</source>
          <target state="translated"><ph id="ph1">&lt;xref:System.ServiceModel.Web.WebGetAttribute&gt;</ph> 属性を適用されたサービス操作は、論理的な取得操作です。</target>       </trans-unit>
        <trans-unit id="107" translate="yes" xml:space="preserve" extradata="MT" uid="T:System.ServiceModel.Web.WebGetAttribute">
          <source>The HTTP GET method is associated with all operations marked with the <ph id="ph1">&lt;xref:System.ServiceModel.Web.WebGetAttribute&gt;</ph> attribute.</source>
          <target state="translated">HTTP GET メソッドは <ph id="ph1">&lt;xref:System.ServiceModel.Web.WebGetAttribute&gt;</ph> 属性付きのすべての操作に関連付けられます。</target>       </trans-unit>
        <trans-unit id="108" translate="yes" xml:space="preserve" extradata="MT" uid="T:System.ServiceModel.Web.WebGetAttribute">
          <source>The following example shows how to use the <ph id="ph1">&lt;xref:System.ServiceModel.Web.WebGetAttribute&gt;</ph> attribute.</source>
          <target state="translated"><ph id="ph1">&lt;xref:System.ServiceModel.Web.WebGetAttribute&gt;</ph> 属性を使用する方法を次のコード例に示します。</target>       </trans-unit>
        <trans-unit id="109" translate="yes" xml:space="preserve" uid="M:System.ServiceModel.Web.WebGetAttribute.#ctor">
          <source>Initializes a new instance of the <ph id="ph1">&lt;see cref="T:System.ServiceModel.Web.WebGetAttribute" /&gt;</ph> class.</source>
          <target state="translated"><ph id="ph1">&lt;see cref="T:System.ServiceModel.Web.WebGetAttribute" /&gt;</ph> クラスの新しいインスタンスを初期化します。</target>       </trans-unit>
        <trans-unit id="110" translate="yes" xml:space="preserve" uid="P:System.ServiceModel.Web.WebGetAttribute.BodyStyle">
          <source>Gets and sets the body style of the messages that are sent to and from the service operation.</source>
          <target state="translated">サービス操作との間で送受信されるメッセージの本文のスタイルを取得して設定します。</target>       </trans-unit>
        <trans-unit id="111" translate="yes" xml:space="preserve" extradata="MT" uid="P:System.ServiceModel.Web.WebGetAttribute.BodyStyle">
          <source>One of the <ph id="ph1">&lt;see cref="T:System.ServiceModel.Web.WebMessageBodyStyle" /&gt;</ph> enumeration values.</source>
          <target state="translated"><ph id="ph1">&lt;see cref="T:System.ServiceModel.Web.WebMessageBodyStyle" /&gt;</ph> 列挙値のいずれか。</target>       </trans-unit>
        <trans-unit id="112" translate="yes" xml:space="preserve" extradata="MT" uid="P:System.ServiceModel.Web.WebGetAttribute.BodyStyle">
          <source>When set to <ph id="ph1">&lt;xref:System.ServiceModel.Web.WebMessageBodyStyle.Bare&gt;</ph>, the result of the service operation is written directly to the body of the response message.</source>
          <target state="translated"><ph id="ph1">&lt;xref:System.ServiceModel.Web.WebMessageBodyStyle.Bare&gt;</ph>に設定する場合、サービス操作の結果は応答メッセージの本文に直接書き込まれます。</target>       </trans-unit>
        <trans-unit id="113" translate="yes" xml:space="preserve" extradata="MT" uid="P:System.ServiceModel.Web.WebGetAttribute.BodyStyle">
          <source>The following example shows how to set the <ph id="ph1">&lt;xref:System.ServiceModel.Web.WebGetAttribute.BodyStyle%2A&gt;</ph> property.</source>
          <target state="translated"><ph id="ph1">&lt;xref:System.ServiceModel.Web.WebGetAttribute.BodyStyle%2A&gt;</ph> プロパティを設定する方法を次の例に示します。</target>       </trans-unit>
        <trans-unit id="114" translate="yes" xml:space="preserve" uid="P:System.ServiceModel.Web.WebGetAttribute.IsBodyStyleSetExplicitly">
          <source>Gets the <ph id="ph1">&lt;see cref="P:System.ServiceModel.Web.WebGetAttribute.IsBodyStyleSetExplicitly" /&gt;</ph> property.</source>
          <target state="translated"><ph id="ph1">&lt;see cref="P:System.ServiceModel.Web.WebGetAttribute.IsBodyStyleSetExplicitly" /&gt;</ph> プロパティを取得します。</target>       </trans-unit>
        <trans-unit id="115" translate="yes" xml:space="preserve" extradata="MT" uid="P:System.ServiceModel.Web.WebGetAttribute.IsBodyStyleSetExplicitly">
          <source>A value that specifies whether the <ph id="ph1">&lt;see cref="P:System.ServiceModel.Web.WebGetAttribute.BodyStyle" /&gt;</ph> property is set.</source>
          <target state="translated"><ph id="ph1">&lt;see cref="P:System.ServiceModel.Web.WebGetAttribute.BodyStyle" /&gt;</ph> プロパティが設定されているかどうかを指定する値。</target>       </trans-unit>
        <trans-unit id="116" translate="yes" xml:space="preserve" extradata="MT" uid="P:System.ServiceModel.Web.WebGetAttribute.IsBodyStyleSetExplicitly">
          <source>This property is designed to be used by the <ph id="ph1">[!INCLUDE[indigo2](~/includes/indigo2-md.md)]</ph> infrastructure and should never be set from user code.</source>
          <target state="translated">このプロパティは、<ph id="ph1">[!INCLUDE[indigo2](~/includes/indigo2-md.md)]</ph> インフラストラクチャによって使用されるように設計されており、ユーザー コードからは設定できません。</target>       </trans-unit>
        <trans-unit id="117" translate="yes" xml:space="preserve" uid="P:System.ServiceModel.Web.WebGetAttribute.IsRequestFormatSetExplicitly">
          <source>Gets the <ph id="ph1">&lt;see cref="P:System.ServiceModel.Web.WebGetAttribute.IsRequestFormatSetExplicitly" /&gt;</ph> property.</source>
          <target state="translated"><ph id="ph1">&lt;see cref="P:System.ServiceModel.Web.WebGetAttribute.IsRequestFormatSetExplicitly" /&gt;</ph> プロパティを取得します。</target>       </trans-unit>
        <trans-unit id="118" translate="yes" xml:space="preserve" extradata="MT" uid="P:System.ServiceModel.Web.WebGetAttribute.IsRequestFormatSetExplicitly">
          <source>A value that specifies whether the <ph id="ph1">&lt;see cref="P:System.ServiceModel.Web.WebGetAttribute.RequestFormat" /&gt;</ph> property was set.</source>
          <target state="translated"><ph id="ph1">&lt;see cref="P:System.ServiceModel.Web.WebGetAttribute.RequestFormat" /&gt;</ph> プロパティが設定されていたかどうかを指定する値。</target>       </trans-unit>
        <trans-unit id="119" translate="yes" xml:space="preserve" extradata="MT" uid="P:System.ServiceModel.Web.WebGetAttribute.IsRequestFormatSetExplicitly">
          <source>This property is designed to be used by the <ph id="ph1">[!INCLUDE[indigo2](~/includes/indigo2-md.md)]</ph> infrastructure and should never be set from user code.</source>
          <target state="translated">このプロパティは、<ph id="ph1">[!INCLUDE[indigo2](~/includes/indigo2-md.md)]</ph> インフラストラクチャによって使用されるように設計されており、ユーザー コードからは設定できません。</target>       </trans-unit>
        <trans-unit id="120" translate="yes" xml:space="preserve" uid="P:System.ServiceModel.Web.WebGetAttribute.IsResponseFormatSetExplicitly">
          <source>Gets the <ph id="ph1">&lt;see cref="P:System.ServiceModel.Web.WebGetAttribute.IsResponseFormatSetExplicitly" /&gt;</ph> property.</source>
          <target state="translated"><ph id="ph1">&lt;see cref="P:System.ServiceModel.Web.WebGetAttribute.IsResponseFormatSetExplicitly" /&gt;</ph> プロパティを取得します。</target>       </trans-unit>
        <trans-unit id="121" translate="yes" xml:space="preserve" extradata="MT" uid="P:System.ServiceModel.Web.WebGetAttribute.IsResponseFormatSetExplicitly">
          <source>A value that specifies whether the <ph id="ph1">&lt;see cref="P:System.ServiceModel.Web.WebGetAttribute.ResponseFormat" /&gt;</ph> property was set.</source>
          <target state="translated"><ph id="ph1">&lt;see cref="P:System.ServiceModel.Web.WebGetAttribute.ResponseFormat" /&gt;</ph> プロパティが設定されていたかどうかを指定する値。</target>       </trans-unit>
        <trans-unit id="122" translate="yes" xml:space="preserve" extradata="MT" uid="P:System.ServiceModel.Web.WebGetAttribute.IsResponseFormatSetExplicitly">
          <source>This property is designed to be used by the <ph id="ph1">[!INCLUDE[indigo2](~/includes/indigo2-md.md)]</ph> infrastructure and should never be set from user code.</source>
          <target state="translated">このプロパティは、<ph id="ph1">[!INCLUDE[indigo2](~/includes/indigo2-md.md)]</ph> インフラストラクチャによって使用されるように設計されており、ユーザー コードからは設定できません。</target>       </trans-unit>
        <trans-unit id="123" translate="yes" xml:space="preserve" uid="P:System.ServiceModel.Web.WebGetAttribute.RequestFormat">
          <source>Gets and sets the <ph id="ph1">&lt;see cref="P:System.ServiceModel.Web.WebGetAttribute.RequestFormat" /&gt;</ph> property.</source>
          <target state="translated"><ph id="ph1">&lt;see cref="P:System.ServiceModel.Web.WebGetAttribute.RequestFormat" /&gt;</ph> プロパティを取得および設定します。</target>       </trans-unit>
        <trans-unit id="124" translate="yes" xml:space="preserve" extradata="MT" uid="P:System.ServiceModel.Web.WebGetAttribute.RequestFormat">
          <source>One of the <ph id="ph1">&lt;see cref="T:System.ServiceModel.Web.WebMessageFormat" /&gt;</ph> enumeration values.</source>
          <target state="translated"><ph id="ph1">&lt;see cref="T:System.ServiceModel.Web.WebMessageFormat" /&gt;</ph> 列挙値のいずれか。</target>       </trans-unit>
        <trans-unit id="125" translate="yes" xml:space="preserve" extradata="MT" uid="P:System.ServiceModel.Web.WebGetAttribute.RequestFormat">
          <source>This property determines the format of requests made to a service operation.</source>
          <target state="translated">このプロパティは、サービス操作に対する要求の形式を決定します。</target>       </trans-unit>
        <trans-unit id="126" translate="yes" xml:space="preserve" extradata="MT" uid="P:System.ServiceModel.Web.WebGetAttribute.RequestFormat">
          <source>The two possible values are <ph id="ph1">`Xml`</ph> and <ph id="ph2">`Json`</ph>.</source>
          <target state="translated">使用できる 2 つの値は <ph id="ph1">`Xml`</ph> と <ph id="ph2">`Json`</ph> です。</target>       </trans-unit>
        <trans-unit id="127" translate="yes" xml:space="preserve" extradata="MT" uid="P:System.ServiceModel.Web.WebGetAttribute.RequestFormat">
          <source>The following example shows how to set the <ph id="ph1">&lt;xref:System.ServiceModel.Web.WebGetAttribute.RequestFormat%2A&gt;</ph> property.</source>
          <target state="translated"><ph id="ph1">&lt;xref:System.ServiceModel.Web.WebGetAttribute.RequestFormat%2A&gt;</ph> プロパティを設定する方法を次の例に示します。</target>       </trans-unit>
        <trans-unit id="128" translate="yes" xml:space="preserve" uid="P:System.ServiceModel.Web.WebGetAttribute.ResponseFormat">
          <source>Gets and sets the <ph id="ph1">&lt;see cref="P:System.ServiceModel.Web.WebGetAttribute.ResponseFormat" /&gt;</ph> property.</source>
          <target state="translated"><ph id="ph1">&lt;see cref="P:System.ServiceModel.Web.WebGetAttribute.ResponseFormat" /&gt;</ph> プロパティを取得および設定します。</target>       </trans-unit>
        <trans-unit id="129" translate="yes" xml:space="preserve" extradata="MT" uid="P:System.ServiceModel.Web.WebGetAttribute.ResponseFormat">
          <source>One of the <ph id="ph1">&lt;see cref="T:System.ServiceModel.Web.WebMessageFormat" /&gt;</ph> enumeration values.</source>
          <target state="translated"><ph id="ph1">&lt;see cref="T:System.ServiceModel.Web.WebMessageFormat" /&gt;</ph> 列挙値のいずれか。</target>       </trans-unit>
        <trans-unit id="130" translate="yes" xml:space="preserve" extradata="MT" uid="P:System.ServiceModel.Web.WebGetAttribute.ResponseFormat">
          <source>This property determines the format of responses sent from a service operation.</source>
          <target state="translated">このプロパティは、サービス操作から送信される応答の形式を決定します。</target>       </trans-unit>
        <trans-unit id="131" translate="yes" xml:space="preserve" extradata="MT" uid="P:System.ServiceModel.Web.WebGetAttribute.ResponseFormat">
          <source>The two possible values are <ph id="ph1">`Xml`</ph> and <ph id="ph2">`Json`</ph>.</source>
          <target state="translated">使用できる 2 つの値は <ph id="ph1">`Xml`</ph> と <ph id="ph2">`Json`</ph> です。</target>       </trans-unit>
        <trans-unit id="132" translate="yes" xml:space="preserve" extradata="MT" uid="P:System.ServiceModel.Web.WebGetAttribute.ResponseFormat">
          <source>The following example shows how to set the <ph id="ph1">&lt;xref:System.ServiceModel.Web.WebGetAttribute.ResponseFormat%2A&gt;</ph> property.</source>
          <target state="translated"><ph id="ph1">&lt;xref:System.ServiceModel.Web.WebGetAttribute.ResponseFormat%2A&gt;</ph> プロパティを設定する方法を次の例に示します。</target>       </trans-unit>
        <trans-unit id="133" translate="yes" xml:space="preserve" uid="M:System.ServiceModel.Web.WebGetAttribute.System#ServiceModel#Description#IOperationBehavior#Validate(System.ServiceModel.Description.OperationDescription)">
          <source>Implements the <ph id="ph1">&lt;see cref="M:System.ServiceModel.Description.IOperationBehavior.Validate(System.ServiceModel.Description.OperationDescription)" /&gt;</ph> method.</source>
          <target state="translated"><ph id="ph1">&lt;see cref="M:System.ServiceModel.Description.IOperationBehavior.Validate(System.ServiceModel.Description.OperationDescription)" /&gt;</ph> メソッドを実装します。</target>       </trans-unit>
        <trans-unit id="134" translate="yes" xml:space="preserve" extradata="MT" uid="M:System.ServiceModel.Web.WebGetAttribute.System#ServiceModel#Description#IOperationBehavior#Validate(System.ServiceModel.Description.OperationDescription)">
          <source>This method does nothing because the <ph id="ph1">&lt;xref:System.ServiceModel.Web.WebGetAttribute&gt;</ph> attribute is a passive operation behavior.</source>
          <target state="translated"><ph id="ph1">&lt;xref:System.ServiceModel.Web.WebGetAttribute&gt;</ph> 属性は受信操作の動作なので、このメソッドは何も実行しません。</target>       </trans-unit>
        <trans-unit id="135" translate="yes" xml:space="preserve" uid="P:System.ServiceModel.Web.WebGetAttribute.UriTemplate">
          <source>Gets and sets the Uniform Resource Identifier (URI) template for the service operation.</source>
          <target state="translated">サービス操作の URI (Uniform Resource Identifier) テンプレートを取得および設定します。</target>       </trans-unit>
        <trans-unit id="136" translate="yes" xml:space="preserve" extradata="MT" uid="P:System.ServiceModel.Web.WebGetAttribute.UriTemplate">
          <source>The URI template for the service operation.</source>
          <target state="translated">サービス操作の URI テンプレート。</target>       </trans-unit>
        <trans-unit id="137" translate="yes" xml:space="preserve" extradata="MT" uid="P:System.ServiceModel.Web.WebGetAttribute.UriTemplate">
          <source>URI templates are used to determine which requests get dispatched to which service operations.</source>
          <target state="translated">URI テンプレートは、どの要求がどのサービス操作にディスパッチされるかを決定するために使用されます。</target>       </trans-unit>
        <trans-unit id="138" translate="yes" xml:space="preserve" extradata="MT" uid="P:System.ServiceModel.Web.WebGetAttribute.UriTemplate">
          <source>URI templates allow you to map a URI or a set of URIs to a service operation.</source>
          <target state="translated">URI テンプレートを使用することで、単一または一連の URI をサービス操作にマップできます。</target>       </trans-unit>
        <trans-unit id="139" translate="yes" xml:space="preserve" extradata="MT" uid="P:System.ServiceModel.Web.WebGetAttribute.UriTemplate">
          <source><ph id="ph1">[!INCLUDE[crabout](~/includes/crabout-md.md)]</ph> URI templates, see <bpt id="p1">[</bpt>UriTemplate and UriTemplateTable<ept id="p1">](~/docs/framework/wcf/feature-details/uritemplate-and-uritemplatetable.md)</ept>.</source>
          <target state="translated"><ph id="ph1">[!INCLUDE[crabout](~/includes/crabout-md.md)]</ph> URI テンプレートを参照してください<bpt id="p1">[</bpt>UriTemplate および UriTemplateTable<ept id="p1">](~/docs/framework/wcf/feature-details/uritemplate-and-uritemplatetable.md)</ept>です。</target>       </trans-unit>
        <trans-unit id="140" translate="yes" xml:space="preserve" extradata="MT" uid="P:System.ServiceModel.Web.WebGetAttribute.UriTemplate">
          <source>The following example shows how to set the <ph id="ph1">&lt;xref:System.ServiceModel.Web.WebGetAttribute.UriTemplate%2A&gt;</ph> property.</source>
          <target state="translated"><ph id="ph1">&lt;xref:System.ServiceModel.Web.WebGetAttribute.UriTemplate%2A&gt;</ph> プロパティを設定する方法を次の例に示します。</target>       </trans-unit>
      </group>
    </body>
  </file>
</xliff>