<Namespace Name="System.Net.WebSockets">
  <Metadata><Meta Name="ms.openlocfilehash" Value="c6a6c821e9db4df56deee5ed857b285847dbd6cf" /><Meta Name="ms.sourcegitcommit" Value="434f60616a9793fa8436744549fc856e94f7a648" /><Meta Name="ms.translationtype" Value="MT" /><Meta Name="ms.contentlocale" Value="ja-JP" /><Meta Name="ms.lasthandoff" Value="08/24/2018" /><Meta Name="ms.locfileid" Value="30735106" /></Metadata><Docs>
    <summary><see cref="N:System.Net.WebSockets" /> 名前空間は、開発者向けに WebSocket インターフェイスのマネージド実装を提供します。</summary>
    <remarks>
      <format type="text/markdown"><![CDATA[  
  
## Remarks  
 一部のクラスで、<xref:System.Net.WebSockets>名前空間は、Windows 7、Windows Vista SP2、および Windows Server 2008 でサポートされます。 ただし、クライアントとサーバーの Websocket の唯一のパブリックの実装は、Windows 8 および Windows Server 2012 でサポートされます。 クラスとクラスの要素、 <xref:System.Net.WebSockets> Windows 7、Windows Vista SP2、および Windows Server 2008 でサポートされている名前空間は抽象クラス。 これにより、アプリケーション開発者を継承し、クライアント Websocket の実際の実装で、これらの抽象クラスを拡張できます。  
  
 ]]></format>
    </remarks>
  </Docs>
</Namespace>