<?xml version="1.0" encoding="utf-8"?>
<xliff xmlns="urn:oasis:names:tc:xliff:document:1.2" xmlns:xsi="http://www.w3.org/2001/XMLSchema-instance" version="1.2" xsi:schemaLocation="urn:oasis:names:tc:xliff:document:1.2 xliff-core-1.2-transitional.xsd">
  <file datatype="xml" original="DropDownList.xml" source-language="en-US" target-language="ja-JP">
    <header>
      <tool tool-id="mdxliff" tool-name="mdxliff" tool-version="1.0-15c36f0" tool-company="Microsoft" />
      <xliffext:skl_file_name xmlns:xliffext="urn:microsoft:content:schema:xliffextensions">02cd5861-7ce2-4a82-b358-31f8435a0ac560a003b1856f168a5ee4ca1a3666f362fdc483af.skl</xliffext:skl_file_name>
      <xliffext:version xmlns:xliffext="urn:microsoft:content:schema:xliffextensions">1.2</xliffext:version>
      <xliffext:ms.openlocfilehash xmlns:xliffext="urn:microsoft:content:schema:xliffextensions">60a003b1856f168a5ee4ca1a3666f362fdc483af</xliffext:ms.openlocfilehash>
      <xliffext:ms.sourcegitcommit xmlns:xliffext="urn:microsoft:content:schema:xliffextensions">d31dc2ede16f6f7bc64e90d9f897ff54c4e3869b</xliffext:ms.sourcegitcommit>
      <xliffext:ms.lasthandoff xmlns:xliffext="urn:microsoft:content:schema:xliffextensions">04/03/2018</xliffext:ms.lasthandoff>
      <xliffext:moniker_ids xmlns:xliffext="urn:microsoft:content:schema:xliffextensions">netframework-4.5.1,netframework-4.5.2,netframework-4.5,netframework-4.6.1,netframework-4.6.2,netframework-4.6,netframework-4.7.1,netframework-4.7</xliffext:moniker_ids>
    </header>
    <body>
      <group id="content" extype="content">
        <trans-unit id="101" translate="yes" xml:space="preserve" uid="T:System.Web.UI.WebControls.DropDownList">
          <source>Represents a control that allows the user to select a single item from a drop-down list.</source>
          <target state="translated">ユーザーがドロップダウン リストから単一の項目を選択できるコントロールを表します。</target>       </trans-unit>
        <trans-unit id="102" translate="yes" xml:space="preserve" extradata="MT" uid="T:System.Web.UI.WebControls.DropDownList">
          <source>In this topic:</source>
          <target state="translated">このトピックの内容:</target>       </trans-unit>
        <trans-unit id="103" translate="yes" xml:space="preserve" extradata="MT" uid="T:System.Web.UI.WebControls.DropDownList">
          <source><bpt id="p1">[</bpt>Introduction<ept id="p1">](#Introduction)</ept></source>
          <target state="translated"><bpt id="p1">[</bpt>はじめに<ept id="p1">](#Introduction)</ept></target>       </trans-unit>
        <trans-unit id="104" translate="yes" xml:space="preserve" extradata="MT" uid="T:System.Web.UI.WebControls.DropDownList">
          <source><bpt id="p1">[</bpt>Accessibility<ept id="p1">](#Accessibility)</ept></source>
          <target state="translated"><bpt id="p1">[</bpt>ユーザー補助<ept id="p1">](#Accessibility)</ept></target>       </trans-unit>
        <trans-unit id="105" translate="yes" xml:space="preserve" extradata="MT" uid="T:System.Web.UI.WebControls.DropDownList">
          <source><bpt id="p1">[</bpt>Declarative Syntax<ept id="p1">](#DeclarativeSyntax)</ept></source>
          <target state="translated"><bpt id="p1">[</bpt>宣言型の構文<ept id="p1">](#DeclarativeSyntax)</ept></target>       </trans-unit>
        <trans-unit id="106" translate="yes" xml:space="preserve" extradata="MT" uid="T:System.Web.UI.WebControls.DropDownList">
          <source>Introduction</source>
          <target state="translated">はじめに</target>       </trans-unit>
        <trans-unit id="107" translate="yes" xml:space="preserve" extradata="MT" uid="T:System.Web.UI.WebControls.DropDownList">
          <source>Use the <ph id="ph1">&lt;xref:System.Web.UI.WebControls.DropDownList&gt;</ph> control to create a single-selection drop-down list control.</source>
          <target state="translated">使用して、<ph id="ph1">&lt;xref:System.Web.UI.WebControls.DropDownList&gt;</ph>単一選択ドロップダウン リスト コントロールを作成するコントロール。</target>       </trans-unit>
        <trans-unit id="108" translate="yes" xml:space="preserve" extradata="MT" uid="T:System.Web.UI.WebControls.DropDownList">
          <source>You can control the appearance of the <ph id="ph1">&lt;xref:System.Web.UI.WebControls.DropDownList&gt;</ph> control by setting the <ph id="ph2">&lt;xref:System.Web.UI.WebControls.DropDownList.BorderColor%2A&gt;</ph>, <ph id="ph3">&lt;xref:System.Web.UI.WebControls.DropDownList.BorderStyle%2A&gt;</ph>, and <ph id="ph4">&lt;xref:System.Web.UI.WebControls.DropDownList.BorderWidth%2A&gt;</ph> properties.</source>
          <target state="translated">外観を制御することができます、<ph id="ph1">&lt;xref:System.Web.UI.WebControls.DropDownList&gt;</ph>コントロールを設定して、 <ph id="ph2">&lt;xref:System.Web.UI.WebControls.DropDownList.BorderColor%2A&gt;</ph>、 <ph id="ph3">&lt;xref:System.Web.UI.WebControls.DropDownList.BorderStyle%2A&gt;</ph>、および<ph id="ph4">&lt;xref:System.Web.UI.WebControls.DropDownList.BorderWidth%2A&gt;</ph>プロパティです。</target>       </trans-unit>
        <trans-unit id="109" translate="yes" xml:space="preserve" extradata="MT" uid="T:System.Web.UI.WebControls.DropDownList">
          <source>To specify the items that you want to appear in the <ph id="ph1">&lt;xref:System.Web.UI.WebControls.DropDownList&gt;</ph> control, place a <ph id="ph2">&lt;xref:System.Web.UI.WebControls.ListItem&gt;</ph> object for each entry between the opening and closing tags of the <ph id="ph3">&lt;xref:System.Web.UI.WebControls.DropDownList&gt;</ph> control.</source>
          <target state="translated">表示する項目を指定する、<ph id="ph1">&lt;xref:System.Web.UI.WebControls.DropDownList&gt;</ph>コントロールを配置、<ph id="ph2">&lt;xref:System.Web.UI.WebControls.ListItem&gt;</ph>開始タグと終了タグの間には、各エントリのオブジェクト、<ph id="ph3">&lt;xref:System.Web.UI.WebControls.DropDownList&gt;</ph>コントロール。</target>       </trans-unit>
        <trans-unit id="110" translate="yes" xml:space="preserve" extradata="MT" uid="T:System.Web.UI.WebControls.DropDownList">
          <source>The <ph id="ph1">&lt;xref:System.Web.UI.WebControls.DropDownList&gt;</ph> control also supports data binding.</source>
          <target state="translated"><ph id="ph1">&lt;xref:System.Web.UI.WebControls.DropDownList&gt;</ph>コントロールには、データ バインディングもサポートしています。</target>       </trans-unit>
        <trans-unit id="111" translate="yes" xml:space="preserve" extradata="MT" uid="T:System.Web.UI.WebControls.DropDownList">
          <source>To bind the control to a data source, create a data source, such as a <ph id="ph1">&lt;xref:System.Collections.ArrayList?displayProperty=nameWithType&gt;</ph> object, that contains the items to display in the control.</source>
          <target state="translated">データ ソースにコントロールをバインドするにはデータ ソースの作成など、<ph id="ph1">&lt;xref:System.Collections.ArrayList?displayProperty=nameWithType&gt;</ph>をコントロールに表示するアイテムを含むオブジェクト。</target>       </trans-unit>
        <trans-unit id="112" translate="yes" xml:space="preserve" extradata="MT" uid="T:System.Web.UI.WebControls.DropDownList">
          <source>Then, use the <ph id="ph1">&lt;xref:System.Web.UI.Control.DataBind%2A?displayProperty=nameWithType&gt;</ph> method to bind the data source to the <ph id="ph2">&lt;xref:System.Web.UI.WebControls.DropDownList&gt;</ph> control.</source>
          <target state="translated">次に、使用、<ph id="ph1">&lt;xref:System.Web.UI.Control.DataBind%2A?displayProperty=nameWithType&gt;</ph>をデータ ソースにバインドするメソッド、<ph id="ph2">&lt;xref:System.Web.UI.WebControls.DropDownList&gt;</ph>コントロール。</target>       </trans-unit>
        <trans-unit id="113" translate="yes" xml:space="preserve" extradata="MT" uid="T:System.Web.UI.WebControls.DropDownList">
          <source>Use the <ph id="ph1">&lt;xref:System.Web.UI.WebControls.DropDownList.SelectedIndex%2A&gt;</ph> property to programmatically determine the index of the item selected by the user from the <ph id="ph2">&lt;xref:System.Web.UI.WebControls.DropDownList&gt;</ph> control.</source>
          <target state="translated">使用して、<ph id="ph1">&lt;xref:System.Web.UI.WebControls.DropDownList.SelectedIndex%2A&gt;</ph>プログラムからユーザーが選択した項目のインデックスを決定するプロパティ、<ph id="ph2">&lt;xref:System.Web.UI.WebControls.DropDownList&gt;</ph>コントロール。</target>       </trans-unit>
        <trans-unit id="114" translate="yes" xml:space="preserve" extradata="MT" uid="T:System.Web.UI.WebControls.DropDownList">
          <source>The index can then be used to retrieve the selected item from the <ph id="ph1">`Items`</ph> collection of the control.</source>
          <target state="translated">選択した項目を取得する、インデックスを使用してできます、<ph id="ph1">`Items`</ph>コントロールのコレクション。</target>       </trans-unit>
        <trans-unit id="115" translate="yes" xml:space="preserve" extradata="MT" uid="T:System.Web.UI.WebControls.DropDownList">
          <source>Accessibility</source>
          <target state="translated">ユーザー補助</target>       </trans-unit>
        <trans-unit id="116" translate="yes" xml:space="preserve" extradata="MT" uid="T:System.Web.UI.WebControls.DropDownList">
          <source>For information about how to configure this control so that it generates markup that conforms to accessibility standards, see <bpt id="p1">[</bpt>Accessibility in Visual Studio and ASP.NET<ept id="p1">](http://msdn.microsoft.com/library/7e3ce9c4-6b7d-4fb1-94b5-72cf2a44fe13)</ept> and <bpt id="p2">[</bpt>ASP.NET Controls and Accessibility<ept id="p2">](http://msdn.microsoft.com/library/847a37e3-ce20-41da-b0d3-7dfb0fdae9a0)</ept>.</source>
          <target state="translated">ユーザー補助の標準に準拠するマークアップを生成するように、このコントロールを構成する方法については、次を参照してください。 <bpt id="p1">[</bpt>Visual Studio と ASP.NET のユーザー補助機能<ept id="p1">](http://msdn.microsoft.com/library/7e3ce9c4-6b7d-4fb1-94b5-72cf2a44fe13)</ept>と<bpt id="p2">[</bpt>ASP.NET コントロールやアクセシビリティ<ept id="p2">](http://msdn.microsoft.com/library/847a37e3-ce20-41da-b0d3-7dfb0fdae9a0)</ept>です。</target>       </trans-unit>
        <trans-unit id="117" translate="yes" xml:space="preserve" extradata="MT" uid="T:System.Web.UI.WebControls.DropDownList">
          <source>Declarative Syntax</source>
          <target state="translated">宣言型の構文</target>       </trans-unit>
        <trans-unit id="118" translate="yes" xml:space="preserve" extradata="MT" uid="T:System.Web.UI.WebControls.DropDownList">
          <source>A Visual Studio Web site project with source code is available to accompany this topic: <bpt id="p1">[</bpt>Download<ept id="p1">](http://go.microsoft.com/fwlink/?LinkId=191893)</ept>.</source>
          <target state="translated">Visual Studio の Web サイト プロジェクトとソース コードは、このトピックで使用可能な:<bpt id="p1">[</bpt>ダウンロード<ept id="p1">](http://go.microsoft.com/fwlink/?LinkId=191893)</ept>です。</target>       </trans-unit>
        <trans-unit id="119" translate="yes" xml:space="preserve" extradata="MT" uid="T:System.Web.UI.WebControls.DropDownList">
          <source>The following code example demonstrates how to create a <ph id="ph1">&lt;xref:System.Web.UI.WebControls.DropDownList&gt;</ph> control that contains four items.</source>
          <target state="translated">次のコード例を作成する方法を示しています、<ph id="ph1">&lt;xref:System.Web.UI.WebControls.DropDownList&gt;</ph>を 4 つの項目を含むコントロールです。</target>       </trans-unit>
        <trans-unit id="120" translate="yes" xml:space="preserve" extradata="MT" uid="T:System.Web.UI.WebControls.DropDownList">
          <source>The following code example demonstrates how to create a <ph id="ph1">&lt;xref:System.Web.UI.WebControls.DropDownList&gt;</ph> control though data binding.</source>
          <target state="translated">次のコード例を作成する方法を示しています、<ph id="ph1">&lt;xref:System.Web.UI.WebControls.DropDownList&gt;</ph>がデータ バインドを制御します。</target>       </trans-unit>
        <trans-unit id="121" translate="yes" xml:space="preserve" uid="M:System.Web.UI.WebControls.DropDownList.#ctor">
          <source>Initializes a new instance of the <ph id="ph1">&lt;see cref="T:System.Web.UI.WebControls.DropDownList" /&gt;</ph> class.</source>
          <target state="translated"><ph id="ph1">&lt;see cref="T:System.Web.UI.WebControls.DropDownList" /&gt;</ph> クラスの新しいインスタンスを初期化します。</target>       </trans-unit>
        <trans-unit id="122" translate="yes" xml:space="preserve" extradata="MT" uid="M:System.Web.UI.WebControls.DropDownList.#ctor">
          <source>Use this constructor to create and initialize a new instance of the <ph id="ph1">&lt;xref:System.Web.UI.WebControls.DropDownList&gt;</ph> class.</source>
          <target state="translated">このコンス トラクターを使用して作成しの新しいインスタンスを初期化、<ph id="ph1">&lt;xref:System.Web.UI.WebControls.DropDownList&gt;</ph>クラスです。</target>       </trans-unit>
        <trans-unit id="123" translate="yes" xml:space="preserve" extradata="MT" uid="M:System.Web.UI.WebControls.DropDownList.#ctor">
          <source>The following code example demonstrates how to create and initialize a new instance of the <ph id="ph1">&lt;xref:System.Web.UI.WebControls.DropDownList&gt;</ph> class.</source>
          <target state="translated">次のコード例を作成しの新しいインスタンスを初期化する方法を示しています、<ph id="ph1">&lt;xref:System.Web.UI.WebControls.DropDownList&gt;</ph>クラスです。</target>       </trans-unit>
        <trans-unit id="124" translate="yes" xml:space="preserve" uid="M:System.Web.UI.WebControls.DropDownList.AddAttributesToRender(System.Web.UI.HtmlTextWriter)">
          <source>An <ph id="ph1">&lt;see cref="T:System.Web.UI.HtmlTextWriter" /&gt;</ph> that represents the output stream that renders HTML contents to the client.</source>
          <target state="translated">HTML コンテンツをクライアントに表示する出力ストリームを表す <ph id="ph1">&lt;see cref="T:System.Web.UI.HtmlTextWriter" /&gt;</ph>。</target>       </trans-unit>
        <trans-unit id="125" translate="yes" xml:space="preserve" uid="M:System.Web.UI.WebControls.DropDownList.AddAttributesToRender(System.Web.UI.HtmlTextWriter)">
          <source>Adds HTML attributes and styles that need to be rendered to the specified <ph id="ph1">&lt;see cref="T:System.Web.UI.HtmlTextWriter" /&gt;</ph> object.</source>
          <target state="translated">指定した <ph id="ph1">&lt;see cref="T:System.Web.UI.HtmlTextWriter" /&gt;</ph> オブジェクトに表示する必要のある HTML 属性およびスタイルを追加します。</target>       </trans-unit>
        <trans-unit id="126" translate="yes" xml:space="preserve" extradata="MT" uid="M:System.Web.UI.WebControls.DropDownList.AddAttributesToRender(System.Web.UI.HtmlTextWriter)">
          <source>This member is used primarily by control developers when deriving a custom control from the <ph id="ph1">&lt;xref:System.Web.UI.WebControls.DropDownList&gt;</ph> class.</source>
          <target state="translated">このメンバーは、主にコントロールの開発者によって使用からカスタム コントロールを派生している場合、<ph id="ph1">&lt;xref:System.Web.UI.WebControls.DropDownList&gt;</ph>クラスです。</target>       </trans-unit>
        <trans-unit id="127" translate="yes" xml:space="preserve" uid="P:System.Web.UI.WebControls.DropDownList.BorderColor">
          <source>Gets or sets the border color of the control.</source>
          <target state="translated">コントロールの境界線の色を取得または設定します。</target>       </trans-unit>
        <trans-unit id="128" translate="yes" xml:space="preserve" extradata="MT" uid="P:System.Web.UI.WebControls.DropDownList.BorderColor">
          <source>A <ph id="ph1">&lt;see cref="T:System.Drawing.Color" /&gt;</ph> that represents the border color of the control.</source>
          <target state="translated">コントロールの境界線の色を表す <ph id="ph1">&lt;see cref="T:System.Drawing.Color" /&gt;</ph>。</target>       </trans-unit>
        <trans-unit id="129" translate="yes" xml:space="preserve" extradata="MT" uid="P:System.Web.UI.WebControls.DropDownList.BorderColor">
          <source>The <ph id="ph1">&lt;xref:System.Web.UI.WebControls.DropDownList.BorderColor%2A&gt;</ph> property is inherited from the <ph id="ph2">&lt;xref:System.Web.UI.WebControls.WebControl&gt;</ph> class and is not applicable to the <ph id="ph3">&lt;xref:System.Web.UI.WebControls.DropDownList&gt;</ph> control.</source>
          <target state="translated"><ph id="ph1">&lt;xref:System.Web.UI.WebControls.DropDownList.BorderColor%2A&gt;</ph>から継承されたプロパティ、<ph id="ph2">&lt;xref:System.Web.UI.WebControls.WebControl&gt;</ph>クラスし、は適用されません、<ph id="ph3">&lt;xref:System.Web.UI.WebControls.DropDownList&gt;</ph>コントロール。</target>       </trans-unit>
        <trans-unit id="130" translate="yes" xml:space="preserve" extradata="MT" uid="P:System.Web.UI.WebControls.DropDownList.BorderColor">
          <source>The following code example demonstrates how to get or set the <ph id="ph1">&lt;xref:System.Web.UI.WebControls.DropDownList.BorderColor%2A&gt;</ph> property in a custom <ph id="ph2">&lt;xref:System.Web.UI.WebControls.DropDownList&gt;</ph> control.</source>
          <target state="translated">次のコード例を取得または設定する方法を示しています、<ph id="ph1">&lt;xref:System.Web.UI.WebControls.DropDownList.BorderColor%2A&gt;</ph>カスタム プロパティ<ph id="ph2">&lt;xref:System.Web.UI.WebControls.DropDownList&gt;</ph>コントロール。</target>       </trans-unit>
        <trans-unit id="131" translate="yes" xml:space="preserve" extradata="MT" uid="P:System.Web.UI.WebControls.DropDownList.BorderColor">
          <source>For information about using custom server controls, see <bpt id="p1">[</bpt>Walkthrough: Developing and Using a Custom Web Server Control<ept id="p1">](http://msdn.microsoft.com/library/6d90782a-a1a4-45a6-b2d4-cf6362b83b08)</ept>.</source>
          <target state="translated">カスタム サーバー コントロールの使用方法の詳細については、次を参照してください。<bpt id="p1">[</bpt>チュートリアル: カスタム Web サーバー コントロールの開発と<ept id="p1">](http://msdn.microsoft.com/library/6d90782a-a1a4-45a6-b2d4-cf6362b83b08)</ept>です。</target>       </trans-unit>
        <trans-unit id="132" translate="yes" xml:space="preserve" uid="P:System.Web.UI.WebControls.DropDownList.BorderStyle">
          <source>Gets or sets the border style of the control.</source>
          <target state="translated">コントロールの境界線スタイルを取得または設定します。</target>       </trans-unit>
        <trans-unit id="133" translate="yes" xml:space="preserve" extradata="MT" uid="P:System.Web.UI.WebControls.DropDownList.BorderStyle">
          <source>One of the <ph id="ph1">&lt;see cref="T:System.Web.UI.WebControls.BorderStyle" /&gt;</ph> values.</source>
          <target state="translated"><ph id="ph1">&lt;see cref="T:System.Web.UI.WebControls.BorderStyle" /&gt;</ph> 値のいずれか 1 つ。</target>       </trans-unit>
        <trans-unit id="134" translate="yes" xml:space="preserve" extradata="MT" uid="P:System.Web.UI.WebControls.DropDownList.BorderStyle">
          <source>The <ph id="ph1">&lt;xref:System.Web.UI.WebControls.DropDownList.BorderStyle%2A&gt;</ph> property is inherited from the <ph id="ph2">&lt;xref:System.Web.UI.WebControls.WebControl&gt;</ph> class and is not applicable to the <ph id="ph3">&lt;xref:System.Web.UI.WebControls.DropDownList&gt;</ph> control.</source>
          <target state="translated"><ph id="ph1">&lt;xref:System.Web.UI.WebControls.DropDownList.BorderStyle%2A&gt;</ph>から継承されたプロパティ、<ph id="ph2">&lt;xref:System.Web.UI.WebControls.WebControl&gt;</ph>クラスし、は適用されません、<ph id="ph3">&lt;xref:System.Web.UI.WebControls.DropDownList&gt;</ph>コントロール。</target>       </trans-unit>
        <trans-unit id="135" translate="yes" xml:space="preserve" uid="P:System.Web.UI.WebControls.DropDownList.BorderWidth">
          <source>Gets or sets the border width for the control.</source>
          <target state="translated">コントロールの境界線の幅を取得または設定します。</target>       </trans-unit>
        <trans-unit id="136" translate="yes" xml:space="preserve" extradata="MT" uid="P:System.Web.UI.WebControls.DropDownList.BorderWidth">
          <source>A <ph id="ph1">&lt;see cref="T:System.Web.UI.WebControls.Unit" /&gt;</ph> that represents the border width for the control.</source>
          <target state="translated">コントロールの境界線の幅を表す <ph id="ph1">&lt;see cref="T:System.Web.UI.WebControls.Unit" /&gt;</ph>。</target>       </trans-unit>
        <trans-unit id="137" translate="yes" xml:space="preserve" extradata="MT" uid="P:System.Web.UI.WebControls.DropDownList.BorderWidth">
          <source>The <ph id="ph1">&lt;xref:System.Web.UI.WebControls.DropDownList.BorderWidth%2A&gt;</ph> property is inherited from the <ph id="ph2">&lt;xref:System.Web.UI.WebControls.WebControl&gt;</ph> class and is not applicable to the <ph id="ph3">&lt;xref:System.Web.UI.WebControls.DropDownList&gt;</ph> control.</source>
          <target state="translated"><ph id="ph1">&lt;xref:System.Web.UI.WebControls.DropDownList.BorderWidth%2A&gt;</ph>から継承されたプロパティ、<ph id="ph2">&lt;xref:System.Web.UI.WebControls.WebControl&gt;</ph>クラスし、は適用されません、<ph id="ph3">&lt;xref:System.Web.UI.WebControls.DropDownList&gt;</ph>コントロール。</target>       </trans-unit>
        <trans-unit id="138" translate="yes" xml:space="preserve" uid="M:System.Web.UI.WebControls.DropDownList.CreateControlCollection">
          <source>Creates a collection to store child controls.</source>
          <target state="translated">子コントロールを格納するコレクションを作成します。</target>       </trans-unit>
        <trans-unit id="139" translate="yes" xml:space="preserve" uid="M:System.Web.UI.WebControls.DropDownList.CreateControlCollection">
          <source>Always returns an <ph id="ph1">&lt;see cref="T:System.Web.UI.EmptyControlCollection" /&gt;</ph>.</source>
          <target state="translated">常に <ph id="ph1">&lt;see cref="T:System.Web.UI.EmptyControlCollection" /&gt;</ph> を返します。</target>       </trans-unit>
        <trans-unit id="140" translate="yes" xml:space="preserve" extradata="MT" uid="M:System.Web.UI.WebControls.DropDownList.CreateControlCollection">
          <source>The following code example demonstrates how to override the <ph id="ph1">&lt;xref:System.Web.UI.WebControls.DropDownList.CreateControlCollection%2A&gt;</ph> method in a custom server control so that it always returns a new instance of the <ph id="ph2">&lt;xref:System.Web.UI.EmptyControlCollection&gt;</ph> class for the <ph id="ph3">&lt;xref:System.Web.UI.WebControls.DropDownList&gt;</ph> control.</source>
          <target state="translated">次のコード例をオーバーライドする方法を示しています、<ph id="ph1">&lt;xref:System.Web.UI.WebControls.DropDownList.CreateControlCollection%2A&gt;</ph>メソッドでカスタム サーバー コントロールの新しいインスタンスを常に返すように、<ph id="ph2">&lt;xref:System.Web.UI.EmptyControlCollection&gt;</ph>のクラス、<ph id="ph3">&lt;xref:System.Web.UI.WebControls.DropDownList&gt;</ph>コントロール。</target>       </trans-unit>
        <trans-unit id="141" translate="yes" xml:space="preserve" extradata="MT" uid="M:System.Web.UI.WebControls.DropDownList.CreateControlCollection">
          <source>For information about using custom server controls, see <bpt id="p1">[</bpt>Walkthrough: Developing and Using a Custom Web Server Control<ept id="p1">](http://msdn.microsoft.com/library/6d90782a-a1a4-45a6-b2d4-cf6362b83b08)</ept>.</source>
          <target state="translated">カスタム サーバー コントロールの使用方法の詳細については、次を参照してください。<bpt id="p1">[</bpt>チュートリアル: カスタム Web サーバー コントロールの開発と<ept id="p1">](http://msdn.microsoft.com/library/6d90782a-a1a4-45a6-b2d4-cf6362b83b08)</ept>です。</target>       </trans-unit>
        <trans-unit id="142" translate="yes" xml:space="preserve" uid="M:System.Web.UI.WebControls.DropDownList.LoadPostData(System.String,System.Collections.Specialized.NameValueCollection)">
          <source>The index within the posted collection that references the content to load.</source>
          <target state="translated">読み込まれる内容を参照する、ポストされたコレクション内のインデックス。</target>       </trans-unit>
        <trans-unit id="143" translate="yes" xml:space="preserve" uid="M:System.Web.UI.WebControls.DropDownList.LoadPostData(System.String,System.Collections.Specialized.NameValueCollection)">
          <source>The collection of all incoming name values posted to the server.</source>
          <target state="translated">サーバーにポストされた受信する名前と値すべてのコレクション。</target>       </trans-unit>
        <trans-unit id="144" translate="yes" xml:space="preserve" uid="M:System.Web.UI.WebControls.DropDownList.LoadPostData(System.String,System.Collections.Specialized.NameValueCollection)">
          <source>Processes postback data for the <ph id="ph1">&lt;see cref="T:System.Web.UI.WebControls.DropDownList" /&gt;</ph> control.</source>
          <target state="translated"><ph id="ph1">&lt;see cref="T:System.Web.UI.WebControls.DropDownList" /&gt;</ph> コントロールのポストバック データを処理します。</target>       </trans-unit>
        <trans-unit id="145" translate="yes" xml:space="preserve" uid="M:System.Web.UI.WebControls.DropDownList.LoadPostData(System.String,System.Collections.Specialized.NameValueCollection)">
          <source><ph id="ph1">&lt;see langword="true" /&gt;</ph> if the <ph id="ph2">&lt;see cref="T:System.Web.UI.WebControls.DropDownList" /&gt;</ph> control's state changes as a result of the postback event; otherwise, <ph id="ph3">&lt;see langword="false" /&gt;</ph>.</source>
          <target state="translated">ポストバック イベントの結果、<ph id="ph2">&lt;see cref="T:System.Web.UI.WebControls.DropDownList" /&gt;</ph> コントロールの状態が変化した場合は <ph id="ph1">&lt;see langword="true" /&gt;</ph>。それ以外の場合は <ph id="ph3">&lt;see langword="false" /&gt;</ph>。</target>       </trans-unit>
        <trans-unit id="146" translate="yes" xml:space="preserve" extradata="MT" uid="M:System.Web.UI.WebControls.DropDownList.LoadPostData(System.String,System.Collections.Specialized.NameValueCollection)">
          <source>The ASP.NET page framework tracks all the server controls that return <ph id="ph1">`true`</ph> from this method call, and then invokes the <ph id="ph2">&lt;xref:System.Web.UI.WebControls.DropDownList.RaisePostDataChangedEvent%2A&gt;</ph> method on the <ph id="ph3">&lt;xref:System.Web.UI.WebControls.DropDownList&gt;</ph> control.</source>
          <target state="translated">ASP.NET ページ フレームワークを返すすべてのサーバー コントロールでは追跡<ph id="ph1">`true`</ph>このメソッドの呼び出しからして呼び出します、<ph id="ph2">&lt;xref:System.Web.UI.WebControls.DropDownList.RaisePostDataChangedEvent%2A&gt;</ph>メソッドを<ph id="ph3">&lt;xref:System.Web.UI.WebControls.DropDownList&gt;</ph>コントロール。</target>       </trans-unit>
        <trans-unit id="147" translate="yes" xml:space="preserve" uid="M:System.Web.UI.WebControls.DropDownList.RaisePostDataChangedEvent">
          <source>Raises events for the <ph id="ph1">&lt;see cref="T:System.Web.UI.WebControls.DropDownList" /&gt;</ph> control when postback occurs.</source>
          <target state="translated">ポストバックが発生したときに <ph id="ph1">&lt;see cref="T:System.Web.UI.WebControls.DropDownList" /&gt;</ph> コントロールのイベントを発生させます。</target>       </trans-unit>
        <trans-unit id="148" translate="yes" xml:space="preserve" extradata="MT" uid="M:System.Web.UI.WebControls.DropDownList.RaisePostDataChangedEvent">
          <source>The ASP.NET page framework calls the <ph id="ph1">&lt;xref:System.Web.UI.WebControls.DropDownList.RaisePostDataChangedEvent%2A&gt;</ph> method on a <ph id="ph2">&lt;xref:System.Web.UI.WebControls.DropDownList&gt;</ph> control when the <ph id="ph3">&lt;xref:System.Web.UI.WebControls.DropDownList.LoadPostData%2A&gt;</ph> method indicates that the state of the list items has changed in the <ph id="ph4">&lt;xref:System.Web.UI.WebControls.DropDownList&gt;</ph> control.</source>
          <target state="translated">ASP.NET ページ フレームワークによって、<ph id="ph1">&lt;xref:System.Web.UI.WebControls.DropDownList.RaisePostDataChangedEvent%2A&gt;</ph>メソッドを<ph id="ph2">&lt;xref:System.Web.UI.WebControls.DropDownList&gt;</ph>タイミングを制御、<ph id="ph3">&lt;xref:System.Web.UI.WebControls.DropDownList.LoadPostData%2A&gt;</ph>メソッドで、一覧の項目の状態が変更されたことを示します、<ph id="ph4">&lt;xref:System.Web.UI.WebControls.DropDownList&gt;</ph>コントロール。</target>       </trans-unit>
        <trans-unit id="149" translate="yes" xml:space="preserve" extradata="MT" uid="M:System.Web.UI.WebControls.DropDownList.RaisePostDataChangedEvent">
          <source>The <ph id="ph1">&lt;xref:System.Web.UI.WebControls.DropDownList.RaisePostDataChangedEvent%2A&gt;</ph> method calls the <ph id="ph2">&lt;xref:System.Web.UI.WebControls.ListControl.OnSelectedIndexChanged%2A&gt;</ph> method to raise the <ph id="ph3">&lt;xref:System.Web.UI.WebControls.ListControl.SelectedIndexChanged&gt;</ph> event.</source>
          <target state="translated"><ph id="ph1">&lt;xref:System.Web.UI.WebControls.DropDownList.RaisePostDataChangedEvent%2A&gt;</ph>メソッドの呼び出し、<ph id="ph2">&lt;xref:System.Web.UI.WebControls.ListControl.OnSelectedIndexChanged%2A&gt;</ph>させる方法、<ph id="ph3">&lt;xref:System.Web.UI.WebControls.ListControl.SelectedIndexChanged&gt;</ph>イベント。</target>       </trans-unit>
        <trans-unit id="150" translate="yes" xml:space="preserve" extradata="MT" uid="M:System.Web.UI.WebControls.DropDownList.RaisePostDataChangedEvent">
          <source>Control developers can override the <ph id="ph1">&lt;xref:System.Web.UI.WebControls.ListControl.OnSelectedIndexChanged%2A&gt;</ph> method to perform custom processing when the user selects items in the control.</source>
          <target state="translated">コントロール開発者、<ph id="ph1">&lt;xref:System.Web.UI.WebControls.ListControl.OnSelectedIndexChanged%2A&gt;</ph>ユーザーがコントロールで項目を選択したときに、カスタム処理を実行するメソッド。</target>       </trans-unit>
        <trans-unit id="151" translate="yes" xml:space="preserve" uid="P:System.Web.UI.WebControls.DropDownList.SelectedIndex">
          <source>Gets or sets the index of the selected item in the <ph id="ph1">&lt;see cref="T:System.Web.UI.WebControls.DropDownList" /&gt;</ph> control.</source>
          <target state="translated"><ph id="ph1">&lt;see cref="T:System.Web.UI.WebControls.DropDownList" /&gt;</ph> コントロール内の選択された項目のインデックスを取得または設定します。</target>       </trans-unit>
        <trans-unit id="152" translate="yes" xml:space="preserve" extradata="MT" uid="P:System.Web.UI.WebControls.DropDownList.SelectedIndex">
          <source>The index of the selected item in the <ph id="ph1">&lt;see cref="T:System.Web.UI.WebControls.DropDownList" /&gt;</ph> control.</source>
          <target state="translated"><ph id="ph1">&lt;see cref="T:System.Web.UI.WebControls.DropDownList" /&gt;</ph> コントロール内の選択された項目のインデックス。</target>       </trans-unit>
        <trans-unit id="153" translate="yes" xml:space="preserve" extradata="MT" uid="P:System.Web.UI.WebControls.DropDownList.SelectedIndex">
          <source>The default value is 0, which selects the first item in the list.</source>
          <target state="translated">既定値は 0 であり、この場合はリストの最初の項目を選択します。</target>       </trans-unit>
        <trans-unit id="154" translate="yes" xml:space="preserve" extradata="MT" uid="P:System.Web.UI.WebControls.DropDownList.SelectedIndex">
          <source>Use the <ph id="ph1">&lt;xref:System.Web.UI.WebControls.DropDownList.SelectedIndex%2A&gt;</ph> property to programmatically specify or determine the index of the selected item from the <ph id="ph2">&lt;xref:System.Web.UI.WebControls.DropDownList&gt;</ph> control.</source>
          <target state="translated">使用して、<ph id="ph1">&lt;xref:System.Web.UI.WebControls.DropDownList.SelectedIndex%2A&gt;</ph>をプログラムで指定またはから選択した項目のインデックスを決定するプロパティ、<ph id="ph2">&lt;xref:System.Web.UI.WebControls.DropDownList&gt;</ph>コントロール。</target>       </trans-unit>
        <trans-unit id="155" translate="yes" xml:space="preserve" extradata="MT" uid="P:System.Web.UI.WebControls.DropDownList.SelectedIndex">
          <source>An item is always selected in the <ph id="ph1">&lt;xref:System.Web.UI.WebControls.DropDownList&gt;</ph> control.</source>
          <target state="translated">項目が常に選択、<ph id="ph1">&lt;xref:System.Web.UI.WebControls.DropDownList&gt;</ph>コントロール。</target>       </trans-unit>
        <trans-unit id="156" translate="yes" xml:space="preserve" extradata="MT" uid="P:System.Web.UI.WebControls.DropDownList.SelectedIndex">
          <source>You cannot clear the selection from every item in the list at the same time.</source>
          <target state="translated">同時に、リスト内のすべての項目から選択を解除することはできません。</target>       </trans-unit>
        <trans-unit id="157" translate="yes" xml:space="preserve" extradata="MT" uid="P:System.Web.UI.WebControls.DropDownList.SelectedIndex">
          <source>The indexes for the items in the <ph id="ph1">&lt;xref:System.Web.UI.WebControls.DropDownList&gt;</ph> control are zero-based.</source>
          <target state="translated">内の項目のインデックス、<ph id="ph1">&lt;xref:System.Web.UI.WebControls.DropDownList&gt;</ph>コントロールは 0 から始まります。</target>       </trans-unit>
        <trans-unit id="158" translate="yes" xml:space="preserve" extradata="MT" uid="P:System.Web.UI.WebControls.DropDownList.SelectedIndex">
          <source>The following code example demonstrates how to use the <ph id="ph1">&lt;xref:System.Web.UI.WebControls.DropDownList.SelectedIndex%2A&gt;</ph> property to determine the selected item in the <ph id="ph2">&lt;xref:System.Web.UI.WebControls.DropDownList&gt;</ph> control.</source>
          <target state="translated">次のコード例を使用する方法を示しています、<ph id="ph1">&lt;xref:System.Web.UI.WebControls.DropDownList.SelectedIndex%2A&gt;</ph>プロパティで選択した項目を<ph id="ph2">&lt;xref:System.Web.UI.WebControls.DropDownList&gt;</ph>コントロール。</target>       </trans-unit>
        <trans-unit id="159" translate="yes" xml:space="preserve" uid="P:System.Web.UI.WebControls.DropDownList.SupportsDisabledAttribute">
          <source>Gets a value that indicates whether the control should set the <ph id="ph1">&lt;see langword="disabled" /&gt;</ph> attribute of the rendered HTML element to "disabled" when the control's <ph id="ph2">&lt;see cref="P:System.Web.UI.WebControls.WebControl.IsEnabled" /&gt;</ph> property is <ph id="ph3">&lt;see langword="false" /&gt;</ph>.</source>
          <target state="translated">コントロールの <ph id="ph2">&lt;see cref="P:System.Web.UI.WebControls.WebControl.IsEnabled" /&gt;</ph> プロパティが <ph id="ph3">&lt;see langword="false" /&gt;</ph> の場合、レンダリングされた HTML 要素の <ph id="ph1">&lt;see langword="disabled" /&gt;</ph> 属性を "無効" に設定するかどうかを示す値を取得します。</target>       </trans-unit>
        <trans-unit id="160" translate="yes" xml:space="preserve" extradata="MT" uid="P:System.Web.UI.WebControls.DropDownList.SupportsDisabledAttribute">
          <source><ph id="ph1">&lt;see langword="true" /&gt;</ph> if the <ph id="ph2">&lt;see cref="P:System.Web.UI.Control.RenderingCompatibility" /&gt;</ph> property indicates an ASP.NET version lower than <bpt id="p1">&lt;c&gt;</bpt>4.0<ept id="p1">&lt;/c&gt;</ept>; otherwise, <ph id="ph3">&lt;see langword="false" /&gt;</ph>.</source>
          <target state="translated"><ph id="ph1">&lt;see langword="true" /&gt;</ph> 場合、<ph id="ph2">&lt;see cref="P:System.Web.UI.Control.RenderingCompatibility" /&gt;</ph>プロパティがより低い ASP.NET のバージョンを示す<bpt id="p1">&lt;c&gt;</bpt>4.0<ept id="p1">&lt;/c&gt;</ept>、それ以外の<ph id="ph3">&lt;see langword="false" /&gt;</ph>します。</target>       </trans-unit>
        <trans-unit id="161" translate="yes" xml:space="preserve" extradata="MT" uid="P:System.Web.UI.WebControls.DropDownList.SupportsDisabledAttribute">
          <source>This property indicates how ASP.NET should render HTML for a control when the control is disabled.</source>
          <target state="translated">このプロパティは、コントロールが無効になっているときに ASP.NET がそのコントロールの HTML をどのように描画するかを示します。</target>       </trans-unit>
        <trans-unit id="162" translate="yes" xml:space="preserve" extradata="MT" uid="P:System.Web.UI.WebControls.DropDownList.SupportsDisabledAttribute">
          <source>If this property is <ph id="ph1">`true`</ph>, ASP.NET renders a <ph id="ph2">`disabled`</ph> attribute when a control is disabled.</source>
          <target state="translated">場合は、このプロパティは<ph id="ph1">`true`</ph>、ASP.NET は表示、<ph id="ph2">`disabled`</ph>属性のコントロールを無効にします。</target>       </trans-unit>
        <trans-unit id="163" translate="yes" xml:space="preserve" extradata="MT" uid="P:System.Web.UI.WebControls.DropDownList.SupportsDisabledAttribute">
          <source>If this property is <ph id="ph1">`false`</ph>, ASP.NET renders a <ph id="ph2">`class`</ph> attribute when a control is disabled.</source>
          <target state="translated">場合は、このプロパティは<ph id="ph1">`false`</ph>、ASP.NET は表示、<ph id="ph2">`class`</ph>属性のコントロールを無効にします。</target>       </trans-unit>
        <trans-unit id="164" translate="yes" xml:space="preserve" extradata="MT" uid="P:System.Web.UI.WebControls.DropDownList.SupportsDisabledAttribute">
          <source>For more information, see <ph id="ph1">&lt;xref:System.Web.UI.WebControls.WebControl.SupportsDisabledAttribute%2A?displayProperty=nameWithType&gt;</ph>.</source>
          <target state="translated">詳細については、「<ph id="ph1">&lt;xref:System.Web.UI.WebControls.WebControl.SupportsDisabledAttribute%2A?displayProperty=nameWithType&gt;</ph>」を参照してください。</target>       </trans-unit>
        <trans-unit id="165" translate="yes" xml:space="preserve" uid="M:System.Web.UI.WebControls.DropDownList.System#Web#UI#IPostBackDataHandler#LoadPostData(System.String,System.Collections.Specialized.NameValueCollection)">
          <source>The key value used to index an entry in the collection.</source>
          <target state="translated">コレクション内のエントリのインデックス指定に使用するキー値。</target>       </trans-unit>
        <trans-unit id="166" translate="yes" xml:space="preserve" uid="M:System.Web.UI.WebControls.DropDownList.System#Web#UI#IPostBackDataHandler#LoadPostData(System.String,System.Collections.Specialized.NameValueCollection)">
          <source>A <ph id="ph1">&lt;see cref="T:System.Collections.Specialized.NameValueCollection" /&gt;</ph> that contains post information.</source>
          <target state="translated">ポスト情報を格納する <ph id="ph1">&lt;see cref="T:System.Collections.Specialized.NameValueCollection" /&gt;</ph>。</target>       </trans-unit>
        <trans-unit id="167" translate="yes" xml:space="preserve" uid="M:System.Web.UI.WebControls.DropDownList.System#Web#UI#IPostBackDataHandler#LoadPostData(System.String,System.Collections.Specialized.NameValueCollection)">
          <source>Processes posted data for the <ph id="ph1">&lt;see cref="T:System.Web.UI.WebControls.DropDownList" /&gt;</ph> control.</source>
          <target state="translated"><ph id="ph1">&lt;see cref="T:System.Web.UI.WebControls.DropDownList" /&gt;</ph> コントロールのポストされたデータを処理します。</target>       </trans-unit>
        <trans-unit id="168" translate="yes" xml:space="preserve" uid="M:System.Web.UI.WebControls.DropDownList.System#Web#UI#IPostBackDataHandler#LoadPostData(System.String,System.Collections.Specialized.NameValueCollection)">
          <source><ph id="ph1">&lt;see langword="true" /&gt;</ph> if the posted content is different from the last posting; otherwise, <ph id="ph2">&lt;see langword="false" /&gt;</ph>.</source>
          <target state="translated">ポストされた内容が前回ポストされた内容と異なる場合は <ph id="ph1">&lt;see langword="true" /&gt;</ph>。それ以外の場合は <ph id="ph2">&lt;see langword="false" /&gt;</ph>。</target>       </trans-unit>
        <trans-unit id="169" translate="yes" xml:space="preserve" uid="M:System.Web.UI.WebControls.DropDownList.System#Web#UI#IPostBackDataHandler#RaisePostDataChangedEvent">
          <source>Raises events for the <ph id="ph1">&lt;see cref="T:System.Web.UI.WebControls.DropDownList" /&gt;</ph> control on postback.</source>
          <target state="translated">ポストバック時に <ph id="ph1">&lt;see cref="T:System.Web.UI.WebControls.DropDownList" /&gt;</ph> コントロールのイベントを発生させます。</target>       </trans-unit>
        <trans-unit id="170" translate="yes" xml:space="preserve" uid="M:System.Web.UI.WebControls.DropDownList.VerifyMultiSelect">
          <source>Always throws an <ph id="ph1">&lt;see cref="T:System.Web.HttpException" /&gt;</ph> exception because multiple selection is not supported for the <ph id="ph2">&lt;see cref="T:System.Web.UI.WebControls.DropDownList" /&gt;</ph> control.</source>
          <target state="translated"><ph id="ph1">&lt;see cref="T:System.Web.HttpException" /&gt;</ph> コントロールでは複数選択がサポートされていないため、常に <ph id="ph2">&lt;see cref="T:System.Web.UI.WebControls.DropDownList" /&gt;</ph> 例外がスローされます。</target>       </trans-unit>
        <trans-unit id="171" translate="yes" xml:space="preserve" extradata="MT" uid="M:System.Web.UI.WebControls.DropDownList.VerifyMultiSelect">
          <source>The <ph id="ph1">&lt;xref:System.Web.UI.WebControls.DropDownList&gt;</ph> control does not support multiple selections and throws an <ph id="ph2">&lt;xref:System.Web.HttpException&gt;</ph> exception.</source>
          <target state="translated"><ph id="ph1">&lt;xref:System.Web.UI.WebControls.DropDownList&gt;</ph>複数の選択とがスローされますが、コントロールはサポートされない、<ph id="ph2">&lt;xref:System.Web.HttpException&gt;</ph>例外。</target>       </trans-unit>
        <trans-unit id="172" translate="yes" xml:space="preserve" uid="M:System.Web.UI.WebControls.DropDownList.VerifyMultiSelect">
          <source>In all cases.</source>
          <target state="translated">すべての場合。</target>       </trans-unit>
      </group>
    </body>
  </file>
</xliff>