<?xml version="1.0" encoding="utf-8"?>
<xliff xmlns="urn:oasis:names:tc:xliff:document:1.2" xmlns:xsi="http://www.w3.org/2001/XMLSchema-instance" version="1.2" xsi:schemaLocation="urn:oasis:names:tc:xliff:document:1.2 xliff-core-1.2-transitional.xsd">
  <file datatype="xml" original="WebPartTransformerCollection.xml" source-language="en-US" target-language="ja-JP">
    <header>
      <tool tool-id="mdxliff" tool-name="mdxliff" tool-version="1.0-15c36f0" tool-company="Microsoft" />
      <xliffext:skl_file_name xmlns:xliffext="urn:microsoft:content:schema:xliffextensions">02cd5861-7ce2-4a82-b358-31f8435a0ac52888998ab3ac55e087fbe5f3949094b6b00e7256.skl</xliffext:skl_file_name>
      <xliffext:version xmlns:xliffext="urn:microsoft:content:schema:xliffextensions">1.2</xliffext:version>
      <xliffext:ms.openlocfilehash xmlns:xliffext="urn:microsoft:content:schema:xliffextensions">2888998ab3ac55e087fbe5f3949094b6b00e7256</xliffext:ms.openlocfilehash>
      <xliffext:ms.sourcegitcommit xmlns:xliffext="urn:microsoft:content:schema:xliffextensions">d31dc2ede16f6f7bc64e90d9f897ff54c4e3869b</xliffext:ms.sourcegitcommit>
      <xliffext:ms.lasthandoff xmlns:xliffext="urn:microsoft:content:schema:xliffextensions">04/03/2018</xliffext:ms.lasthandoff>
      <xliffext:moniker_ids xmlns:xliffext="urn:microsoft:content:schema:xliffextensions">netframework-4.5.1,netframework-4.5.2,netframework-4.5,netframework-4.6.1,netframework-4.6.2,netframework-4.6,netframework-4.7.1,netframework-4.7</xliffext:moniker_ids>
    </header>
    <body>
      <group id="content" extype="content">
        <trans-unit id="101" translate="yes" xml:space="preserve" uid="T:System.Web.UI.WebControls.WebParts.WebPartTransformerCollection">
          <source>Provides a collection of <ph id="ph1">&lt;see cref="T:System.Web.UI.WebControls.WebParts.WebPartTransformer" /&gt;</ph> objects.</source>
          <target state="translated"><ph id="ph1">&lt;see cref="T:System.Web.UI.WebControls.WebParts.WebPartTransformer" /&gt;</ph> オブジェクトのコレクションを提供します。</target>       </trans-unit>
        <trans-unit id="102" translate="yes" xml:space="preserve" extradata="MT" uid="T:System.Web.UI.WebControls.WebParts.WebPartTransformerCollection">
          <source>The <ph id="ph1">&lt;xref:System.Web.UI.WebControls.WebParts.WebPartTransformerCollection&gt;</ph> class is a collection of <ph id="ph2">&lt;xref:System.Web.UI.WebControls.WebParts.WebPartTransformer&gt;</ph> objects, typically used by the <ph id="ph3">&lt;xref:System.Web.UI.WebControls.WebParts.WebPartConnection&gt;</ph> object to manage a set of <ph id="ph4">&lt;xref:System.Web.UI.WebControls.WebParts.WebPartTransformer&gt;</ph> objects for a connection.</source>
          <target state="translated"><ph id="ph1">&lt;xref:System.Web.UI.WebControls.WebParts.WebPartTransformerCollection&gt;</ph>クラスは、コレクションの<ph id="ph2">&lt;xref:System.Web.UI.WebControls.WebParts.WebPartTransformer&gt;</ph>で通常使用される、オブジェクト、<ph id="ph3">&lt;xref:System.Web.UI.WebControls.WebParts.WebPartConnection&gt;</ph>のセットを管理するオブジェクト<ph id="ph4">&lt;xref:System.Web.UI.WebControls.WebParts.WebPartTransformer&gt;</ph>接続オブジェクトです。</target>       </trans-unit>
        <trans-unit id="103" translate="yes" xml:space="preserve" extradata="MT" uid="T:System.Web.UI.WebControls.WebParts.WebPartTransformerCollection">
          <source>The transformers related to a Web Parts connection can be retrieved through the <ph id="ph1">&lt;xref:System.Web.UI.WebControls.WebParts.WebPartConnection.Transformers%2A&gt;</ph> property.</source>
          <target state="translated">Web パーツの接続に関連するトランスフォーマーを使用して取得できます、<ph id="ph1">&lt;xref:System.Web.UI.WebControls.WebParts.WebPartConnection.Transformers%2A&gt;</ph>プロパティです。</target>       </trans-unit>
        <trans-unit id="104" translate="yes" xml:space="preserve" uid="M:System.Web.UI.WebControls.WebParts.WebPartTransformerCollection.#ctor">
          <source>Initializes a new instance of the <ph id="ph1">&lt;see cref="T:System.Web.UI.WebControls.WebParts.WebPartTransformerCollection" /&gt;</ph> class.</source>
          <target state="translated"><ph id="ph1">&lt;see cref="T:System.Web.UI.WebControls.WebParts.WebPartTransformerCollection" /&gt;</ph> クラスの新しいインスタンスを初期化します。</target>       </trans-unit>
        <trans-unit id="105" translate="yes" xml:space="preserve" uid="M:System.Web.UI.WebControls.WebParts.WebPartTransformerCollection.Add(System.Web.UI.WebControls.WebParts.WebPartTransformer)">
          <source>The <ph id="ph1">&lt;see cref="T:System.Web.UI.WebControls.WebParts.WebPartTransformer" /&gt;</ph> to be added to the end of the <ph id="ph2">&lt;see cref="T:System.Web.UI.WebControls.WebParts.WebPartTransformerCollection" /&gt;</ph>.</source>
          <target state="translated"><ph id="ph1">&lt;see cref="T:System.Web.UI.WebControls.WebParts.WebPartTransformer" /&gt;</ph> の末尾に追加する <ph id="ph2">&lt;see cref="T:System.Web.UI.WebControls.WebParts.WebPartTransformerCollection" /&gt;</ph>。</target>       </trans-unit>
        <trans-unit id="106" translate="yes" xml:space="preserve" uid="M:System.Web.UI.WebControls.WebParts.WebPartTransformerCollection.Add(System.Web.UI.WebControls.WebParts.WebPartTransformer)">
          <source>Adds an object to the end of the collection.</source>
          <target state="translated">コレクションの末尾にオブジェクトを追加します。</target>       </trans-unit>
        <trans-unit id="107" translate="yes" xml:space="preserve" uid="M:System.Web.UI.WebControls.WebParts.WebPartTransformerCollection.Add(System.Web.UI.WebControls.WebParts.WebPartTransformer)">
          <source>The index at which <ph id="ph1">&lt;paramref name="transformer" /&gt;</ph> has been added.</source>
          <target state="translated"><ph id="ph1">&lt;paramref name="transformer" /&gt;</ph> が追加された位置のインデックス。</target>       </trans-unit>
        <trans-unit id="108" translate="yes" xml:space="preserve" uid="M:System.Web.UI.WebControls.WebParts.WebPartTransformerCollection.Contains(System.Web.UI.WebControls.WebParts.WebPartTransformer)">
          <source>A <ph id="ph1">&lt;see cref="T:System.Web.UI.WebControls.WebParts.WebPartTransformer" /&gt;</ph> that is checked to determine whether it is in the collection.</source>
          <target state="translated">コレクション内にあるかどうかを判断するためにチェックする <ph id="ph1">&lt;see cref="T:System.Web.UI.WebControls.WebParts.WebPartTransformer" /&gt;</ph>。</target>       </trans-unit>
        <trans-unit id="109" translate="yes" xml:space="preserve" uid="M:System.Web.UI.WebControls.WebParts.WebPartTransformerCollection.Contains(System.Web.UI.WebControls.WebParts.WebPartTransformer)">
          <source>Returns a value indicating whether a particular transformer exists in the collection.</source>
          <target state="translated">特定のトランスフォーマーがコレクション内に存在するかどうかを示す値を返します。</target>       </trans-unit>
        <trans-unit id="110" translate="yes" xml:space="preserve" uid="M:System.Web.UI.WebControls.WebParts.WebPartTransformerCollection.Contains(System.Web.UI.WebControls.WebParts.WebPartTransformer)">
          <source>A Boolean value that indicates whether a particular transformer is in the collection.</source>
          <target state="translated">特定のトランスフォーマーがコレクション内に存在するかどうかを示すブール値。</target>       </trans-unit>
        <trans-unit id="111" translate="yes" xml:space="preserve" extradata="MT" uid="M:System.Web.UI.WebControls.WebParts.WebPartTransformerCollection.Contains(System.Web.UI.WebControls.WebParts.WebPartTransformer)">
          <source>The <ph id="ph1">&lt;xref:System.Web.UI.WebControls.WebParts.WebPartTransformerCollection.Contains%2A&gt;</ph> method enables you to check a particular <ph id="ph2">&lt;xref:System.Web.UI.WebControls.WebParts.WebPartTransformer&gt;</ph> object and determine whether it is part of a <ph id="ph3">&lt;xref:System.Web.UI.WebControls.WebParts.WebPartTransformerCollection&gt;</ph> object.</source>
          <target state="translated"><ph id="ph1">&lt;xref:System.Web.UI.WebControls.WebParts.WebPartTransformerCollection.Contains%2A&gt;</ph>メソッドでは、特定を確認することができます<ph id="ph2">&lt;xref:System.Web.UI.WebControls.WebParts.WebPartTransformer&gt;</ph>オブジェクトし、の一部であるかどうかを判断、<ph id="ph3">&lt;xref:System.Web.UI.WebControls.WebParts.WebPartTransformerCollection&gt;</ph>オブジェクト。</target>       </trans-unit>
        <trans-unit id="112" translate="yes" xml:space="preserve" uid="M:System.Web.UI.WebControls.WebParts.WebPartTransformerCollection.CopyTo(System.Web.UI.WebControls.WebParts.WebPartTransformer[],System.Int32)">
          <source>An array of <ph id="ph1">&lt;see cref="T:System.Web.UI.WebControls.WebParts.WebPartTransformer" /&gt;</ph> objects to contain the copied collection.</source>
          <target state="translated">コピーされたコレクションを格納する <ph id="ph1">&lt;see cref="T:System.Web.UI.WebControls.WebParts.WebPartTransformer" /&gt;</ph> オブジェクトの配列。</target>       </trans-unit>
        <trans-unit id="113" translate="yes" xml:space="preserve" uid="M:System.Web.UI.WebControls.WebParts.WebPartTransformerCollection.CopyTo(System.Web.UI.WebControls.WebParts.WebPartTransformer[],System.Int32)">
          <source>The starting point in the array at which to place the collection contents.</source>
          <target state="translated">コレクションの内容を配置する位置を示す、配列内の開始点。</target>       </trans-unit>
        <trans-unit id="114" translate="yes" xml:space="preserve" uid="M:System.Web.UI.WebControls.WebParts.WebPartTransformerCollection.CopyTo(System.Web.UI.WebControls.WebParts.WebPartTransformer[],System.Int32)">
          <source>Copies the collection to an array of <ph id="ph1">&lt;see cref="T:System.Web.UI.WebControls.WebParts.WebPartTransformer" /&gt;</ph> objects.</source>
          <target state="translated">コレクションを <ph id="ph1">&lt;see cref="T:System.Web.UI.WebControls.WebParts.WebPartTransformer" /&gt;</ph> オブジェクトの配列にコピーします。</target>       </trans-unit>
        <trans-unit id="115" translate="yes" xml:space="preserve" extradata="MT" uid="M:System.Web.UI.WebControls.WebParts.WebPartTransformerCollection.CopyTo(System.Web.UI.WebControls.WebParts.WebPartTransformer[],System.Int32)">
          <source>The <ph id="ph1">&lt;xref:System.Web.UI.WebControls.WebParts.WebPartTransformerCollection.CopyTo%2A&gt;</ph> method is useful when you want to assemble a custom array that can contain all the <ph id="ph2">&lt;xref:System.Web.UI.WebControls.WebParts.WebPartTransformer&gt;</ph> objects in the <ph id="ph3">&lt;xref:System.Web.UI.WebControls.WebParts.WebPartTransformerCollection&gt;</ph> collection, a subset of those objects, or a superset of those objects.</source>
          <target state="translated"><ph id="ph1">&lt;xref:System.Web.UI.WebControls.WebParts.WebPartTransformerCollection.CopyTo%2A&gt;</ph>メソッドは、すべてを含めることができるカスタムの配列を構築する場合に便利です、<ph id="ph2">&lt;xref:System.Web.UI.WebControls.WebParts.WebPartTransformer&gt;</ph>内のオブジェクト、<ph id="ph3">&lt;xref:System.Web.UI.WebControls.WebParts.WebPartTransformerCollection&gt;</ph>コレクション、それらのオブジェクトのサブセットまたはそれらのオブジェクトのスーパー セットです。</target>       </trans-unit>
        <trans-unit id="116" translate="yes" xml:space="preserve" uid="M:System.Web.UI.WebControls.WebParts.WebPartTransformerCollection.IndexOf(System.Web.UI.WebControls.WebParts.WebPartTransformer)">
          <source>A <ph id="ph1">&lt;see cref="T:System.Web.UI.WebControls.WebParts.WebPartTransformer" /&gt;</ph> that is a member of the collection.</source>
          <target state="translated">コレクションのメンバーである <ph id="ph1">&lt;see cref="T:System.Web.UI.WebControls.WebParts.WebPartTransformer" /&gt;</ph>。</target>       </trans-unit>
        <trans-unit id="117" translate="yes" xml:space="preserve" uid="M:System.Web.UI.WebControls.WebParts.WebPartTransformerCollection.IndexOf(System.Web.UI.WebControls.WebParts.WebPartTransformer)">
          <source>Returns the position of a particular member in the collection.</source>
          <target state="translated">コレクションの特定のメンバーの位置を返します。</target>       </trans-unit>
        <trans-unit id="118" translate="yes" xml:space="preserve" uid="M:System.Web.UI.WebControls.WebParts.WebPartTransformerCollection.IndexOf(System.Web.UI.WebControls.WebParts.WebPartTransformer)">
          <source>An integer that indicates the position of a particular object in the collection.</source>
          <target state="translated">コレクション内で特定のオブジェクトの位置を示す整数。</target>       </trans-unit>
        <trans-unit id="119" translate="yes" xml:space="preserve" uid="M:System.Web.UI.WebControls.WebParts.WebPartTransformerCollection.Insert(System.Int32,System.Web.UI.WebControls.WebParts.WebPartTransformer)">
          <source>The zero-based index at which a value should be inserted.</source>
          <target state="translated">値を挿入する位置の、0 から始まるインデックス。</target>       </trans-unit>
        <trans-unit id="120" translate="yes" xml:space="preserve" uid="M:System.Web.UI.WebControls.WebParts.WebPartTransformerCollection.Insert(System.Int32,System.Web.UI.WebControls.WebParts.WebPartTransformer)">
          <source>The <ph id="ph1">&lt;see cref="T:System.Web.UI.WebControls.WebParts.WebPartTransformer" /&gt;</ph> to insert.</source>
          <target state="translated">挿入する <ph id="ph1">&lt;see cref="T:System.Web.UI.WebControls.WebParts.WebPartTransformer" /&gt;</ph>。</target>       </trans-unit>
        <trans-unit id="121" translate="yes" xml:space="preserve" uid="M:System.Web.UI.WebControls.WebParts.WebPartTransformerCollection.Insert(System.Int32,System.Web.UI.WebControls.WebParts.WebPartTransformer)">
          <source>Inserts a transformer into the <ph id="ph1">&lt;see cref="T:System.Web.UI.WebControls.WebParts.WebPartTransformerCollection" /&gt;</ph> collection at the specified index.</source>
          <target state="translated">トランスフォーマーを <ph id="ph1">&lt;see cref="T:System.Web.UI.WebControls.WebParts.WebPartTransformerCollection" /&gt;</ph> コレクション内の指定したインデックス位置に挿入します。</target>       </trans-unit>
        <trans-unit id="122" translate="yes" xml:space="preserve" uid="P:System.Web.UI.WebControls.WebParts.WebPartTransformerCollection.IsReadOnly">
          <source>Gets a value indicating whether the collection is read-only.</source>
          <target state="translated">コレクションが読み取り専用かどうかを示す値を取得します。</target>       </trans-unit>
        <trans-unit id="123" translate="yes" xml:space="preserve" extradata="MT" uid="P:System.Web.UI.WebControls.WebParts.WebPartTransformerCollection.IsReadOnly">
          <source><ph id="ph1">&lt;see langword="true" /&gt;</ph> if the collection and its items cannot be changed; otherwise, <ph id="ph2">&lt;see langword="false" /&gt;</ph>.</source>
          <target state="translated">コレクションとその項目を変更できない場合は <ph id="ph1">&lt;see langword="true" /&gt;</ph>。それ以外の場合は <ph id="ph2">&lt;see langword="false" /&gt;</ph>。</target>       </trans-unit>
        <trans-unit id="124" translate="yes" xml:space="preserve" uid="P:System.Web.UI.WebControls.WebParts.WebPartTransformerCollection.Item(System.Int32)">
          <source>The index of a particular <ph id="ph1">&lt;see cref="T:System.Web.UI.WebControls.WebParts.WebPartTransformer" /&gt;</ph> in a collection.</source>
          <target state="translated">特定の <ph id="ph1">&lt;see cref="T:System.Web.UI.WebControls.WebParts.WebPartTransformer" /&gt;</ph> の、コレクション内でのインデックス。</target>       </trans-unit>
        <trans-unit id="125" translate="yes" xml:space="preserve" uid="P:System.Web.UI.WebControls.WebParts.WebPartTransformerCollection.Item(System.Int32)">
          <source>Returns a member of the collection based on its position in the collection.</source>
          <target state="translated">コレクションにおける位置に基づいてコレクションのメンバーを返します。</target>       </trans-unit>
        <trans-unit id="126" translate="yes" xml:space="preserve" extradata="MT" uid="P:System.Web.UI.WebControls.WebParts.WebPartTransformerCollection.Item(System.Int32)">
          <source>The <ph id="ph1">&lt;see cref="T:System.Web.UI.WebControls.WebParts.WebPartTransformer" /&gt;</ph> located at <ph id="ph2">&lt;paramref name="index" /&gt;</ph>.</source>
          <target state="translated"><ph id="ph2">&lt;paramref name="index" /&gt;</ph> にある <ph id="ph1">&lt;see cref="T:System.Web.UI.WebControls.WebParts.WebPartTransformer" /&gt;</ph>。</target>       </trans-unit>
        <trans-unit id="127" translate="yes" xml:space="preserve" uid="M:System.Web.UI.WebControls.WebParts.WebPartTransformerCollection.Remove(System.Web.UI.WebControls.WebParts.WebPartTransformer)">
          <source>The <ph id="ph1">&lt;see cref="T:System.Web.UI.WebControls.WebParts.WebPartTransformer" /&gt;</ph> to remove from the collection.</source>
          <target state="translated">コレクションから削除する <ph id="ph1">&lt;see cref="T:System.Web.UI.WebControls.WebParts.WebPartTransformer" /&gt;</ph>。</target>       </trans-unit>
        <trans-unit id="128" translate="yes" xml:space="preserve" uid="M:System.Web.UI.WebControls.WebParts.WebPartTransformerCollection.Remove(System.Web.UI.WebControls.WebParts.WebPartTransformer)">
          <source>Removes the first occurrence of a specific transformer.</source>
          <target state="translated">最初に見つかった特定のトランスフォーマーを削除します。</target>       </trans-unit>
      </group>
    </body>
  </file>
</xliff>